dnspod_web/__init__.py
dnspod_web/__init__.pyc
dnspod_web/app.py
dnspod_web/app.pyc
dnspod_web/dnspod.py
dnspod_web/dnspod.pyc
dnspod_web/css/bootstrap.css
dnspod_web/template/domain.html
dnspod_web/template/domain_sub.html
dnspod_web/template/index.html
dnspod_web/template/login.html
dnspod_web/template/message.html
dnspod_web/template/record.html
dnspod_web/template/record_sub.html
dnspod_web/template/recordcreatef.html
dnspod_web-3.0.0.dist-info/LICENSE
dnspod_web-3.0.0.dist-info/METADATA
dnspod_web-3.0.0.dist-info/WHEEL
dnspod_web-3.0.0.dist-info/entry_points.txt
dnspod_web-3.0.0.dist-info/top_level.txt
dnspod_web-3.0.0.dist-info/RECORD
