Metadata-Version: 2.1
Name: dnspod-web
Version: 3.0.0
Summary: DNSPod API Python Web Example
Home-page: https://github.com/likexian/dnspod-api-python-web
Author: Li Kexian
Author-email: 1175571+likexian@users.noreply.github.com
License: UNKNOWN
Platform: UNKNOWN
Classifier: Programming Language :: Python :: 3
Classifier: License :: OSI Approved :: Apache Software License
Classifier: Operating System :: OS Independent
Requires-Python: >=2.6
Requires-Dist: flask
Requires-Dist: requests
